herodotus/__init__.py
herodotus/decorators.py
herodotus-0.1.0.dist-info/LICENSE
herodotus-0.1.0.dist-info/WHEEL
herodotus-0.1.0.dist-info/METADATA
herodotus-0.1.0.dist-info/RECORD
